wrappedbrowser/__init__.py
wrappedbrowser/errors.py
wrappedbrowser/wrappedbrowser.py
wrappedbrowser-0.1.5.dist-info/AUTHORS.rst
wrappedbrowser-0.1.5.dist-info/LICENSE
wrappedbrowser-0.1.5.dist-info/METADATA
wrappedbrowser-0.1.5.dist-info/WHEEL
wrappedbrowser-0.1.5.dist-info/top_level.txt
wrappedbrowser-0.1.5.dist-info/RECORD
