Metadata-Version: 2.1
Name: wrappedbrowser
Version: 0.1.5
Summary: A wrapper around the webbrowser module of the standard library.
Home-page: https://github.com/woodpecker324/wrappedbrowser
Author: woodpecker324
Author-email: woodpecker324@protonmail.com
License: MIT license
Keywords: wrappedbrowser
Platform: UNKNOWN
Classifier: Development Status :: 2 - Pre-Alpha
Classifier: Intended Audience :: Developers
Classifier: License :: OSI Approved :: MIT License
Classifier: Natural Language :: English
Classifier: Programming Language :: Python :: 3
Classifier: Programming Language :: Python :: 3.6
Classifier: Programming Language :: Python :: 3.7
